{
    "body": "Quo rerum qui perspiciatis nobis quidem magni sunt pariatur. Quam officia nihil enim soluta et deserunt vel. Deleniti cumque unde reiciendis et vitae et minus.\nPerspiciatis quae voluptatem est dolorem explicabo suscipit. Aut qui consequatur ex. Quos distinctio omnis illo. Temporibus dolor quo delectus dolorum esse rerum. Et est quia ut. Mollitia laboriosam quia quam ad quis ipsa.\nQui expedita magnam commodi accusantium quae iure. Sunt consequatur quidem et ea et odio. Totam saepe eius quis. Aspernatur dolore aut nulla porro quam quo est quidem quas.\nDolores sed eos. Debitis repudiandae dolor et. Sed et magnam sunt non commodi odit. Ipsum quas earum ex non sint laborum.",
    "title": "Et similique itaque quia pariatur aut",
    "genre": "RPG",
    "publisher": "Ebert Inc",
    "year": 1994,
    "previewImage": "/wesley-tingey--l4UCK06uNM-unsplash.jpg"
}