{
    "body": "Molestias quo et animi ab laborum. Aliquam expedita culpa sunt nam. Laboriosam expedita tempore. Repellendus provident labore maxime eligendi expedita voluptatem tempore dolorum. Autem ipsum ipsum consequuntur assumenda quasi eligendi modi autem. Esse minus similique quo.\nEx qui voluptate esse. Recusandae vitae doloribus reiciendis quaerat id delectus. Culpa delectus debitis molestias impedit. Eaque ad perferendis quae dolorem quaerat doloremque aut culpa. Distinctio temporibus amet. Expedita cumque quas.\nQuidem repellat reiciendis voluptas qui a debitis tempora. Sapiente sequi ducimus esse consequuntur. Rerum ullam eligendi tempora quam beatae esse itaque incidunt. Eius maiores dignissimos tempore. Qui dicta rerum eius.",
    "createdAt": "2023-01-15T10:26:19.095Z",
    "title": "Possimus quisquam repudiandae animi",
    "genre": "Simulator",
    "publisher": "Hilll - Schuppe",
    "developer": "Effertz - Runte",
    "gameRelease": "1996-02-13T21:38:12.475Z",
    "previewImage": "/images/reviews-ph-5.webp"
}