{
    "createdAt": "2023-01-15T10:12:19.062Z",
    "publishedAt": "Sun, 15 Jan 2023 10:12:19 GMT",
    "body": "Eius accusamus natus. Repudiandae eaque ab laboriosam esse id totam totam eos. Rerum adipisci veniam. Minus error sapiente est suscipit debitis rem minus animi. Architecto libero temporibus enim tenetur amet. Molestias voluptate soluta quaerat vero tempora.\nTotam iure recusandae quas adipisci odit consequuntur. Nostrum cum velit repudiandae amet. Ipsam laudantium tenetur illum maxime dicta neque hic. Unde provident excepturi accusamus nisi. Voluptatibus dolore accusantium optio.\nMinima facere porro nesciunt eligendi. Facere dignissimos et dolorum eius delectus architecto rerum. Molestiae iste aliquam ipsam laudantium soluta consequatur error ex. Nihil nostrum dolorem deserunt.\nBlanditiis harum eum excepturi facilis molestias rerum. Explicabo adipisci nulla deleniti asperiores. Fuga modi quisquam est itaque.",
    "title": "Facere nam placeat",
    "previewImage": "/images/news/news-ph-4.webp"
}