{
    "createdAt": "2022-06-05T14:49:46.513Z",
    "publishedAt": "Sun, 05 Jun 2022 14:49:46 GMT",
    "body": "Modi ratione dignissimos non et praesentium voluptatem rerum. Ipsum ea culpa qui quas eveniet id eum. Omnis fugiat quidem iure qui voluptas culpa voluptatum. Rem recusandae eos. Illo accusamus possimus quo.\nNihil in aut eos molestiae commodi ipsam. Quod eaque officiis omnis illum quo aliquid. Rerum magni quidem. Voluptatibus consequuntur molestiae. Optio dolores nisi autem aut et sunt magni recusandae.\nPerferendis labore non eveniet sequi. Modi pariatur eveniet repellendus hic temporibus ab. Qui autem sint et iusto. Deleniti suscipit veniam ut cupiditate voluptatem optio. Saepe totam enim enim et voluptate laborum voluptates. Consequatur et saepe quaerat id quo qui et est quasi.\nEt nihil quaerat quo dolorem est saepe voluptatem sint et. Omnis eius saepe corrupti nisi. Ut est eaque asperiores velit veniam quae enim. Ratione nihil quisquam quia dolorem. Ad maxime aut quae earum officia aperiam dolor sit sit. Quibusdam nobis fugit.\nQuidem ut ea ratione modi. Quis et eaque quidem eveniet doloremque doloremque et. Enim aspernatur alias tempore natus maiores sed. Recusandae ut quaerat sunt. Deserunt voluptatum dolorem ad quisquam.\nEst totam nemo ea reiciendis. Enim officia sint. Iste laboriosam consequatur et doloremque voluptas minus dignissimos vel. Iure veritatis alias voluptas.",
    "title": "Similique aut fugit consequuntur corporis est",
    "previewImage": "/images/review_placeholder_1.jpg"
}